setup.py
lynkpy/__init__.py
lynkpy/image.py
lynkpy/logger.py
lynkpy.egg-info/PKG-INFO
lynkpy.egg-info/SOURCES.txt
lynkpy.egg-info/dependency_links.txt
lynkpy.egg-info/requires.txt
lynkpy.egg-info/top_level.txt