Metadata-Version: 2.1
Name: lynkpy
Version: 0.0.5
Summary: basic utilities
Home-page: 
Author: Siddharth
Author-email: ssiddharth408@gmail.com
Requires-Python: >=3.8
